{
  "title": "Example Objective",
  "description": "This is what an <strong>objective description</strong> looks like!",
  "validation_fields": [
    {
      "name": "answer1",
      "type": "text",
      "placeholder": "type your answer here",
      "label": "What is the name of the company that makes TwilioQuest?"
    },
    {
      "name": "answer2",
      "type": "text",
      "placeholder": "type your answer here",
      "label": "What is 2 + 2? Write the numerical response below."
    },
    {
      "name": "answer3",
      "type": "text",
      "placeholder": "type your answer here",
      "label": "Did you like the TwilioQuest game"
    },
    {
      "name": "answer4",
      "type": "text",
      "placeholder": "type your answer here",
      "label": "Is it free to use Twilio?"
    }
  ],
  "rewards": {
    "xp": 100,
    "items": [["item1", 1], ["item2", 2], ["item3", 3], ["item4", 4]]
  }
}
